Metadata-Version: 2.1
Name: superops-talon
Version: 0.3
Summary: Mailgun library to extract message quotations and signatures (talon-1.6.0)
Home-page: https://pypi.org/project/superops-talon/
Author: Superops
Author-email: app.integrations@superops.ai
License: APACHE2
License-File: LICENSE
